simple_mq/__init__.py
simple_mq/core.py
redis_simple_mq-1.1.0.dist-info/licenses/LICENSE
redis_simple_mq-1.1.0.dist-info/WHEEL
redis_simple_mq-1.1.0.dist-info/METADATA
redis_simple_mq-1.1.0.dist-info/RECORD
